FineTune_Mistral/__init__.py
FineTune_Mistral/fine_tune.py
FineTune_Mistral-0.1.14.dist-info/LICENSE
FineTune_Mistral-0.1.14.dist-info/METADATA
FineTune_Mistral-0.1.14.dist-info/WHEEL
FineTune_Mistral-0.1.14.dist-info/entry_points.txt
FineTune_Mistral-0.1.14.dist-info/top_level.txt
FineTune_Mistral-0.1.14.dist-info/RECORD
